docs/source/conf.py
pycurator/__init__.py
pycurator/_typing.py
pycurator/cli.py
pycurator/collectors/__init__.py
pycurator/collectors/base.py
pycurator/collectors/term_collectors/__init__.py
pycurator/collectors/term_collectors/dryad.py
pycurator/collectors/term_collectors/zenodo.py
pycurator/collectors/term_type_collectors/__init__.py
pycurator/collectors/term_type_collectors/dataverse.py
pycurator/collectors/term_type_collectors/figshare.py
pycurator/collectors/term_type_collectors/kaggle.py
pycurator/collectors/term_type_collectors/papers_with_code.py
pycurator/collectors/type_collectors/__init__.py
pycurator/collectors/type_collectors/open_ml.py
pycurator/collectors/utils/__init__.py
pycurator/collectors/utils/saving.py
pycurator/collectors/utils/validating.py
pycurator/gui/__init__.py
pycurator/gui/controller.py
pycurator/gui/interface.py
pycurator/gui/model.py
pycurator/gui/ui_utils.py
pycurator/gui/view/__init__.py
pycurator/gui/view/landing_page.py
pycurator/gui/view/page.py
pycurator/gui/view/run_page.py
pycurator/gui/view/selection_page.py
pycurator/gui/view/view.py
tests/__init__.py
tests/conftest.py
tests/test_collectors.py
tests/test_saving.py
tests/test_validating.py
pycurator-0.1.2.dist-info/METADATA
pycurator-0.1.2.dist-info/WHEEL
pycurator-0.1.2.dist-info/entry_points.txt
pycurator-0.1.2.dist-info/top_level.txt
pycurator-0.1.2.dist-info/RECORD
